spyglass/__init__.py
spyglass/_version.py
spyglass/settings.py
spyglass/behavior/__init__.py
spyglass/behavior/v1/__init__.py
spyglass/behavior/v1/core.py
spyglass/behavior/v1/moseq.py
spyglass/common/__init__.py
spyglass/common/common_behav.py
spyglass/common/common_dandi.py
spyglass/common/common_device.py
spyglass/common/common_dio.py
spyglass/common/common_ephys.py
spyglass/common/common_filter.py
spyglass/common/common_interval.py
spyglass/common/common_lab.py
spyglass/common/common_nwbfile.py
spyglass/common/common_position.py
spyglass/common/common_region.py
spyglass/common/common_sensors.py
spyglass/common/common_session.py
spyglass/common/common_subject.py
spyglass/common/common_task.py
spyglass/common/common_usage.py
spyglass/common/common_user.py
spyglass/common/common_version.py
spyglass/common/errors.py
spyglass/common/populate_all_common.py
spyglass/common/signal_processing.py
spyglass/common/prepopulate/__init__.py
spyglass/common/prepopulate/prepopulate.py
spyglass/data_import/__init__.py
spyglass/data_import/insert_sessions.py
spyglass/decoding/__init__.py
spyglass/decoding/decoding_merge.py
spyglass/decoding/utils.py
spyglass/decoding/v0/__init__.py
spyglass/decoding/v0/clusterless.py
spyglass/decoding/v0/core.py
spyglass/decoding/v0/dj_decoder_conversion.py
spyglass/decoding/v0/sorted_spikes.py
spyglass/decoding/v0/utils.py
spyglass/decoding/v0/visualization.py
spyglass/decoding/v0/visualization_1D_view.py
spyglass/decoding/v0/visualization_2D_view.py
spyglass/decoding/v1/__init__.py
spyglass/decoding/v1/clusterless.py
spyglass/decoding/v1/core.py
spyglass/decoding/v1/dj_decoder_conversion.py
spyglass/decoding/v1/sorted_spikes.py
spyglass/decoding/v1/utils.py
spyglass/decoding/v1/waveform_features.py
spyglass/lfp/__init__.py
spyglass/lfp/lfp_electrode.py
spyglass/lfp/lfp_imported.py
spyglass/lfp/lfp_merge.py
spyglass/lfp/analysis/__init__.py
spyglass/lfp/analysis/v1/__init__.py
spyglass/lfp/analysis/v1/lfp_band.py
spyglass/lfp/v1/__init__.py
spyglass_neuro-0.5.5.dist-info/METADATA
spyglass_neuro-0.5.5.dist-info/WHEEL
spyglass_neuro-0.5.5.dist-info/licenses/LICENSE
spyglass_neuro-0.5.5.dist-info/RECORD
