Metadata-Version: 2.4
Name: spyglass-neuro
Version: 0.5.5
Summary: Neuroscience data analysis framework for reproducible research
Project-URL: Homepage, https://github.com/LorenFrankLab/spyglass
Project-URL: Bug Tracker, https://github.com/LorenFrankLab/spyglass/issues
Author-email: Loren Frank <loren.frank@ucsf.edu>, Kyu Hyun Lee <kyuhyun.lee@ucsf.edu>, Eric Denovellis <eric.denovellis@ucsf.edu>, Ryan Ly <rly@lbl.gov>, Daniel Gramling <daniel.gramling@ucsf.edu>, Chris Brozdowski <chris.broz@ucsf.edu>, Samuel Bray <sam.bray@ucsf.edu>
License: Copyright (c) 2020-present Loren Frank
License-File: LICENSE
Keywords: data analysis,datajoint,electrophysiology,kachery,neuroscience,nwb,reproducible,research,sortingview,spike sorting,spikeinterface
Classifier: License :: OSI Approved :: MIT License
Classifier: Operating System :: OS Independent
Classifier: Programming Language :: Python :: 3
Requires-Python: <3.13,>=3.9
Requires-Dist: black[jupyter]
Requires-Dist: bottleneck
Requires-Dist: dask
Requires-Dist: datajoint>=0.14.4
Requires-Dist: hdmf>=3.4.6
Requires-Dist: ipympl
Requires-Dist: matplotlib
Requires-Dist: ndx-franklab-novela>=0.1.0
Requires-Dist: ndx-pose
Requires-Dist: non-local-detector
Requires-Dist: numpy
Requires-Dist: opencv-python
Requires-Dist: panel>=1.4.0
Requires-Dist: position-tools>=0.1.0
Requires-Dist: probeinterface<0.3.0
Requires-Dist: pubnub<6.4.0
Requires-Dist: pydotplus
Requires-Dist: pynwb<3,>=2.2.0
Requires-Dist: ripple-detection
Requires-Dist: seaborn
Requires-Dist: sortingview>=0.11
Requires-Dist: spikeinterface<0.100,>=0.99.1
Requires-Dist: track-linearization>=2.3
Provides-Extra: dlc
Requires-Dist: deeplabcut[tf]; extra == 'dlc'
Requires-Dist: ffmpeg; extra == 'dlc'
Provides-Extra: docs
Requires-Dist: hatch; extra == 'docs'
Requires-Dist: jupytext; extra == 'docs'
Requires-Dist: mike; extra == 'docs'
Requires-Dist: mkdocs; extra == 'docs'
Requires-Dist: mkdocs-exclude; extra == 'docs'
Requires-Dist: mkdocs-exclude-search; extra == 'docs'
Requires-Dist: mkdocs-gen-files; extra == 'docs'
Requires-Dist: mkdocs-jupyter; extra == 'docs'
Requires-Dist: mkdocs-literate-nav; extra == 'docs'
Requires-Dist: mkdocs-material; extra == 'docs'
Requires-Dist: mkdocs-mermaid2-plugin; extra == 'docs'
Requires-Dist: mkdocstrings[python]; extra == 'docs'
Provides-Extra: moseq-cpu
Requires-Dist: jax-moseq; extra == 'moseq-cpu'
Requires-Dist: jax[cpu]; extra == 'moseq-cpu'
Requires-Dist: keypoint-moseq; extra == 'moseq-cpu'
Provides-Extra: moseq-gpu
Requires-Dist: jax-moseq[cuda12]; extra == 'moseq-gpu'
Requires-Dist: jax[cuda12]; extra == 'moseq-gpu'
Requires-Dist: keypoint-moseq; extra == 'moseq-gpu'
Provides-Extra: test
Requires-Dist: codecov; extra == 'test'
Requires-Dist: docker; extra == 'test'
Requires-Dist: ghostipy; extra == 'test'
Requires-Dist: kachery; extra == 'test'
Requires-Dist: kachery-client; extra == 'test'
Requires-Dist: kachery-cloud>=0.4.0; extra == 'test'
Requires-Dist: opencv-python-headless; extra == 'test'
Requires-Dist: pre-commit; extra == 'test'
Requires-Dist: pytest; extra == 'test'
Requires-Dist: pytest-cov; extra == 'test'
Requires-Dist: pytest-xvfb; extra == 'test'
